primoutils/__init__.py
numerosPrimos_javivi-1.0.dist-info/LICENSE.txt
numerosPrimos_javivi-1.0.dist-info/METADATA
numerosPrimos_javivi-1.0.dist-info/WHEEL
numerosPrimos_javivi-1.0.dist-info/top_level.txt
numerosPrimos_javivi-1.0.dist-info/RECORD
